<?xml version="1.0" encoding="UTF-8"?>
<catalog xmlns="urn:oasis:names:tc:entity:xmlns:xml:catalog">
<!--DITA Abbreviated Form Domain-->

   <group><!-- System ID (URL) catalog entries -->
      <system systemId="urn:oasis:names:tc:dita:rnc:abbreviateDomainMod.rnc:1.3"
              uri="rnc/abbreviateDomainMod.rnc"/>
      <system systemId="urn:oasis:names:tc:dita:rnc:abbreviateDomainMod.rnc"
              uri="rnc/abbreviateDomainMod.rnc"/>
      <system systemId="urn:oasis:names:tc:dita:rnc:concept.rnc:1.3"
              uri="rnc/concept.rnc"/>
      <system systemId="urn:oasis:names:tc:dita:rnc:concept.rnc"
              uri="rnc/concept.rnc"/>
      <system systemId="urn:oasis:names:tc:dita:rnc:conceptMod.rnc:1.3"
              uri="rnc/conceptMod.rnc"/>
      <system systemId="urn:oasis:names:tc:dita:rnc:conceptMod.rnc"
              uri="rnc/conceptMod.rnc"/>
      <system systemId="urn:oasis:names:tc:dita:rnc:ditabase.rnc:1.3"
              uri="rnc/ditabase.rnc"/>
      <system systemId="urn:oasis:names:tc:dita:rnc:ditabase.rnc"
              uri="rnc/ditabase.rnc"/>
      <system systemId="urn:oasis:names:tc:dita:rnc:equationDomainMod.rnc:1.3"
              uri="rnc/equationDomainMod.rnc"/>
      <system systemId="urn:oasis:names:tc:dita:rnc:equationDomainMod.rnc"
              uri="rnc/equationDomainMod.rnc"/>
      <system systemId="urn:oasis:names:tc:dita:rnc:generalTask.rnc:1.3"
              uri="rnc/generalTask.rnc"/>
      <system systemId="urn:oasis:names:tc:dita:rnc:generalTask.rnc"
              uri="rnc/generalTask.rnc"/>
      <system systemId="urn:oasis:names:tc:dita:rnc:glossary.rnc:1.3"
              uri="rnc/glossary.rnc"/>
      <system systemId="urn:oasis:names:tc:dita:rnc:glossary.rnc"
              uri="rnc/glossary.rnc"/>
      <system systemId="urn:oasis:names:tc:dita:rnc:glossaryMod.rnc:1.3"
              uri="rnc/glossaryMod.rnc"/>
      <system systemId="urn:oasis:names:tc:dita:rnc:glossaryMod.rnc"
              uri="rnc/glossaryMod.rnc"/>
      <system systemId="urn:oasis:names:tc:dita:rnc:glossentry.rnc:1.3"
              uri="rnc/glossentry.rnc"/>
      <system systemId="urn:oasis:names:tc:dita:rnc:glossentry.rnc"
              uri="rnc/glossentry.rnc"/>
      <system systemId="urn:oasis:names:tc:dita:rnc:glossentryMod.rnc:1.3"
              uri="rnc/glossentryMod.rnc"/>
      <system systemId="urn:oasis:names:tc:dita:rnc:glossentryMod.rnc"
              uri="rnc/glossentryMod.rnc"/>
      <system systemId="urn:oasis:names:tc:dita:rnc:glossgroup.rnc:1.3"
              uri="rnc/glossgroup.rnc"/>
      <system systemId="urn:oasis:names:tc:dita:rnc:glossgroup.rnc"
              uri="rnc/glossgroup.rnc"/>
      <system systemId="urn:oasis:names:tc:dita:rnc:glossgroupMod.rnc:1.3"
              uri="rnc/glossgroupMod.rnc"/>
      <system systemId="urn:oasis:names:tc:dita:rnc:glossgroupMod.rnc"
              uri="rnc/glossgroupMod.rnc"/>
      <system systemId="urn:oasis:names:tc:dita:rnc:glossrefDomainMod.rnc:1.3"
              uri="rnc/glossrefDomainMod.rnc"/>
      <system systemId="urn:oasis:names:tc:dita:rnc:glossrefDomainMod.rnc"
              uri="rnc/glossrefDomainMod.rnc"/>
      <system systemId="urn:oasis:names:tc:dita:rnc:map.rnc:1.3" uri="rnc/map.rnc"/>
      <system systemId="urn:oasis:names:tc:dita:rnc:map.rnc" uri="rnc/map.rnc"/>
      <system systemId="urn:oasis:names:tc:dita:rnc:markupDomainMod.rnc:1.3"
              uri="rnc/markupDomainMod.rnc"/>
      <system systemId="urn:oasis:names:tc:dita:rnc:markupDomainMod.rnc"
              uri="rnc/markupDomainMod.rnc"/>
      <system systemId="urn:oasis:names:tc:dita:rnc:mathmlDomainMod.rnc:1.3"
              uri="rnc/mathmlDomainMod.rnc"/>
      <system systemId="urn:oasis:names:tc:dita:rnc:mathmlDomainMod.rnc"
              uri="rnc/mathmlDomainMod.rnc"/>
      <system systemId="urn:oasis:names:tc:dita:rnc:programmingDomainMod.rnc:1.3"
              uri="rnc/programmingDomainMod.rnc"/>
      <system systemId="urn:oasis:names:tc:dita:rnc:programmingDomainMod.rnc"
              uri="rnc/programmingDomainMod.rnc"/>
      <system systemId="urn:oasis:names:tc:dita:rnc:reference.rnc:1.3"
              uri="rnc/reference.rnc"/>
      <system systemId="urn:oasis:names:tc:dita:rnc:reference.rnc"
              uri="rnc/reference.rnc"/>
      <system systemId="urn:oasis:names:tc:dita:rnc:referenceMod.rnc:1.3"
              uri="rnc/referenceMod.rnc"/>
      <system systemId="urn:oasis:names:tc:dita:rnc:referenceMod.rnc"
              uri="rnc/referenceMod.rnc"/>
      <system systemId="urn:oasis:names:tc:dita:rnc:releaseManagementDomainMod.rnc:1.3"
              uri="rnc/releaseManagementDomainMod.rnc"/>
      <system systemId="urn:oasis:names:tc:dita:rnc:releaseManagementDomainMod.rnc"
              uri="rnc/releaseManagementDomainMod.rnc"/>
      <system systemId="urn:oasis:names:tc:dita:rnc:softwareDomainMod.rnc:1.3"
              uri="rnc/softwareDomainMod.rnc"/>
      <system systemId="urn:oasis:names:tc:dita:rnc:softwareDomainMod.rnc"
              uri="rnc/softwareDomainMod.rnc"/>
      <system systemId="urn:oasis:names:tc:dita:rnc:strictTaskbodyConstraintMod.rnc:1.3"
              uri="rnc/strictTaskbodyConstraintMod.rnc"/>
      <system systemId="urn:oasis:names:tc:dita:rnc:strictTaskbodyConstraintMod.rnc"
              uri="rnc/strictTaskbodyConstraintMod.rnc"/>
      <system systemId="urn:oasis:names:tc:dita:rnc:svgDomainMod.rnc:1.3"
              uri="rnc/svgDomainMod.rnc"/>
      <system systemId="urn:oasis:names:tc:dita:rnc:svgDomainMod.rnc"
              uri="rnc/svgDomainMod.rnc"/>
      <system systemId="urn:oasis:names:tc:dita:rnc:task.rnc:1.3" uri="rnc/task.rnc"/>
      <system systemId="urn:oasis:names:tc:dita:rnc:task.rnc" uri="rnc/task.rnc"/>
      <system systemId="urn:oasis:names:tc:dita:rnc:taskMod.rnc:1.3"
              uri="rnc/taskMod.rnc"/>
      <system systemId="urn:oasis:names:tc:dita:rnc:taskMod.rnc"
              uri="rnc/taskMod.rnc"/>
      <system systemId="urn:oasis:names:tc:dita:rnc:taskreqDomainMod.rnc:1.3"
              uri="rnc/taskreqDomainMod.rnc"/>
      <system systemId="urn:oasis:names:tc:dita:rnc:taskreqDomainMod.rnc"
              uri="rnc/taskreqDomainMod.rnc"/>
      <system systemId="urn:oasis:names:tc:dita:rnc:topic.rnc:1.3"
              uri="rnc/topic.rnc"/>
      <system systemId="urn:oasis:names:tc:dita:rnc:topic.rnc" uri="rnc/topic.rnc"/>
      <system systemId="urn:oasis:names:tc:dita:rnc:troubleshooting.rnc:1.3"
              uri="rnc/troubleshooting.rnc"/>
      <system systemId="urn:oasis:names:tc:dita:rnc:troubleshooting.rnc"
              uri="rnc/troubleshooting.rnc"/>
      <system systemId="urn:oasis:names:tc:dita:rnc:troubleshootingMod.rnc:1.3"
              uri="rnc/troubleshootingMod.rnc"/>
      <system systemId="urn:oasis:names:tc:dita:rnc:troubleshootingMod.rnc"
              uri="rnc/troubleshootingMod.rnc"/>
      <system systemId="urn:oasis:names:tc:dita:rnc:uiDomainMod.rnc:1.3"
              uri="rnc/uiDomainMod.rnc"/>
      <system systemId="urn:oasis:names:tc:dita:rnc:uiDomainMod.rnc"
              uri="rnc/uiDomainMod.rnc"/>
      <system systemId="urn:oasis:names:tc:dita:rnc:xmlDomainMod.rnc:1.3"
              uri="rnc/xmlDomainMod.rnc"/>
      <system systemId="urn:oasis:names:tc:dita:rnc:xmlDomainMod.rnc"
              uri="rnc/xmlDomainMod.rnc"/>
   </group>
   <group><!-- Public ID (URN) catalog entries -->
      <uri name="urn:oasis:names:tc:dita:rnc:abbreviateDomainMod.rnc:1.3"
           uri="rnc/abbreviateDomainMod.rnc"/>
      <uri name="urn:oasis:names:tc:dita:rnc:abbreviateDomainMod.rnc"
           uri="rnc/abbreviateDomainMod.rnc"/>
      <uri name="urn:oasis:names:tc:dita:rnc:concept.rnc:1.3"
           uri="rnc/concept.rnc"/>
      <uri name="urn:oasis:names:tc:dita:rnc:concept.rnc" uri="rnc/concept.rnc"/>
      <uri name="urn:oasis:names:tc:dita:rnc:conceptMod.rnc:1.3"
           uri="rnc/conceptMod.rnc"/>
      <uri name="urn:oasis:names:tc:dita:rnc:conceptMod.rnc"
           uri="rnc/conceptMod.rnc"/>
      <uri name="urn:oasis:names:tc:dita:rnc:ditabase.rnc:1.3"
           uri="rnc/ditabase.rnc"/>
      <uri name="urn:oasis:names:tc:dita:rnc:ditabase.rnc" uri="rnc/ditabase.rnc"/>
      <uri name="urn:oasis:names:tc:dita:rnc:equationDomainMod.rnc:1.3"
           uri="rnc/equationDomainMod.rnc"/>
      <uri name="urn:oasis:names:tc:dita:rnc:equationDomainMod.rnc"
           uri="rnc/equationDomainMod.rnc"/>
      <uri name="urn:oasis:names:tc:dita:rnc:generalTask.rnc:1.3"
           uri="rnc/generalTask.rnc"/>
      <uri name="urn:oasis:names:tc:dita:rnc:generalTask.rnc"
           uri="rnc/generalTask.rnc"/>
      <uri name="urn:oasis:names:tc:dita:rnc:glossary.rnc:1.3"
           uri="rnc/glossary.rnc"/>
      <uri name="urn:oasis:names:tc:dita:rnc:glossary.rnc" uri="rnc/glossary.rnc"/>
      <uri name="urn:oasis:names:tc:dita:rnc:glossaryMod.rnc:1.3"
           uri="rnc/glossaryMod.rnc"/>
      <uri name="urn:oasis:names:tc:dita:rnc:glossaryMod.rnc"
           uri="rnc/glossaryMod.rnc"/>
      <uri name="urn:oasis:names:tc:dita:rnc:glossentry.rnc:1.3"
           uri="rnc/glossentry.rnc"/>
      <uri name="urn:oasis:names:tc:dita:rnc:glossentry.rnc"
           uri="rnc/glossentry.rnc"/>
      <uri name="urn:oasis:names:tc:dita:rnc:glossentryMod.rnc:1.3"
           uri="rnc/glossentryMod.rnc"/>
      <uri name="urn:oasis:names:tc:dita:rnc:glossentryMod.rnc"
           uri="rnc/glossentryMod.rnc"/>
      <uri name="urn:oasis:names:tc:dita:rnc:glossgroup.rnc:1.3"
           uri="rnc/glossgroup.rnc"/>
      <uri name="urn:oasis:names:tc:dita:rnc:glossgroup.rnc"
           uri="rnc/glossgroup.rnc"/>
      <uri name="urn:oasis:names:tc:dita:rnc:glossgroupMod.rnc:1.3"
           uri="rnc/glossgroupMod.rnc"/>
      <uri name="urn:oasis:names:tc:dita:rnc:glossgroupMod.rnc"
           uri="rnc/glossgroupMod.rnc"/>
      <uri name="urn:oasis:names:tc:dita:rnc:glossrefDomainMod.rnc:1.3"
           uri="rnc/glossrefDomainMod.rnc"/>
      <uri name="urn:oasis:names:tc:dita:rnc:glossrefDomainMod.rnc"
           uri="rnc/glossrefDomainMod.rnc"/>
      <uri name="urn:oasis:names:tc:dita:rnc:map.rnc:1.3" uri="rnc/map.rnc"/>
      <uri name="urn:oasis:names:tc:dita:rnc:map.rnc" uri="rnc/map.rnc"/>
      <uri name="urn:oasis:names:tc:dita:rnc:markupDomainMod.rnc:1.3"
           uri="rnc/markupDomainMod.rnc"/>
      <uri name="urn:oasis:names:tc:dita:rnc:markupDomainMod.rnc"
           uri="rnc/markupDomainMod.rnc"/>
      <uri name="urn:oasis:names:tc:dita:rnc:mathmlDomainMod.rnc:1.3"
           uri="rnc/mathmlDomainMod.rnc"/>
      <uri name="urn:oasis:names:tc:dita:rnc:mathmlDomainMod.rnc"
           uri="rnc/mathmlDomainMod.rnc"/>
      <uri name="urn:oasis:names:tc:dita:rnc:programmingDomainMod.rnc:1.3"
           uri="rnc/programmingDomainMod.rnc"/>
      <uri name="urn:oasis:names:tc:dita:rnc:programmingDomainMod.rnc"
           uri="rnc/programmingDomainMod.rnc"/>
      <uri name="urn:oasis:names:tc:dita:rnc:reference.rnc:1.3"
           uri="rnc/reference.rnc"/>
      <uri name="urn:oasis:names:tc:dita:rnc:reference.rnc"
           uri="rnc/reference.rnc"/>
      <uri name="urn:oasis:names:tc:dita:rnc:referenceMod.rnc:1.3"
           uri="rnc/referenceMod.rnc"/>
      <uri name="urn:oasis:names:tc:dita:rnc:referenceMod.rnc"
           uri="rnc/referenceMod.rnc"/>
      <uri name="urn:oasis:names:tc:dita:rnc:releaseManagementDomainMod.rnc:1.3"
           uri="rnc/releaseManagementDomainMod.rnc"/>
      <uri name="urn:oasis:names:tc:dita:rnc:releaseManagementDomainMod.rnc"
           uri="rnc/releaseManagementDomainMod.rnc"/>
      <uri name="urn:oasis:names:tc:dita:rnc:softwareDomainMod.rnc:1.3"
           uri="rnc/softwareDomainMod.rnc"/>
      <uri name="urn:oasis:names:tc:dita:rnc:softwareDomainMod.rnc"
           uri="rnc/softwareDomainMod.rnc"/>
      <uri name="urn:oasis:names:tc:dita:rnc:strictTaskbodyConstraintMod.rnc:1.3"
           uri="rnc/strictTaskbodyConstraintMod.rnc"/>
      <uri name="urn:oasis:names:tc:dita:rnc:strictTaskbodyConstraintMod.rnc"
           uri="rnc/strictTaskbodyConstraintMod.rnc"/>
      <uri name="urn:oasis:names:tc:dita:rnc:svgDomainMod.rnc:1.3"
           uri="rnc/svgDomainMod.rnc"/>
      <uri name="urn:oasis:names:tc:dita:rnc:svgDomainMod.rnc"
           uri="rnc/svgDomainMod.rnc"/>
      <uri name="urn:oasis:names:tc:dita:rnc:task.rnc:1.3" uri="rnc/task.rnc"/>
      <uri name="urn:oasis:names:tc:dita:rnc:task.rnc" uri="rnc/task.rnc"/>
      <uri name="urn:oasis:names:tc:dita:rnc:taskMod.rnc:1.3"
           uri="rnc/taskMod.rnc"/>
      <uri name="urn:oasis:names:tc:dita:rnc:taskMod.rnc" uri="rnc/taskMod.rnc"/>
      <uri name="urn:oasis:names:tc:dita:rnc:taskreqDomainMod.rnc:1.3"
           uri="rnc/taskreqDomainMod.rnc"/>
      <uri name="urn:oasis:names:tc:dita:rnc:taskreqDomainMod.rnc"
           uri="rnc/taskreqDomainMod.rnc"/>
      <uri name="urn:oasis:names:tc:dita:rnc:topic.rnc:1.3" uri="rnc/topic.rnc"/>
      <uri name="urn:oasis:names:tc:dita:rnc:topic.rnc" uri="rnc/topic.rnc"/>
      <uri name="urn:oasis:names:tc:dita:rnc:troubleshooting.rnc:1.3"
           uri="rnc/troubleshooting.rnc"/>
      <uri name="urn:oasis:names:tc:dita:rnc:troubleshooting.rnc"
           uri="rnc/troubleshooting.rnc"/>
      <uri name="urn:oasis:names:tc:dita:rnc:troubleshootingMod.rnc:1.3"
           uri="rnc/troubleshootingMod.rnc"/>
      <uri name="urn:oasis:names:tc:dita:rnc:troubleshootingMod.rnc"
           uri="rnc/troubleshootingMod.rnc"/>
      <uri name="urn:oasis:names:tc:dita:rnc:uiDomainMod.rnc:1.3"
           uri="rnc/uiDomainMod.rnc"/>
      <uri name="urn:oasis:names:tc:dita:rnc:uiDomainMod.rnc"
           uri="rnc/uiDomainMod.rnc"/>
      <uri name="urn:oasis:names:tc:dita:rnc:xmlDomainMod.rnc:1.3"
           uri="rnc/xmlDomainMod.rnc"/>
      <uri name="urn:oasis:names:tc:dita:rnc:xmlDomainMod.rnc"
           uri="rnc/xmlDomainMod.rnc"/>
   </group>
</catalog>
